bin_fixedrec-1.0.1.dist-info/licenses/LICENSE
fixedrec/__init__.py
fixedrec/__main__.py
fixedrec/cli.py
fixedrec/parser.py
bin_fixedrec-1.0.1.dist-info/METADATA
bin_fixedrec-1.0.1.dist-info/WHEEL
bin_fixedrec-1.0.1.dist-info/entry_points.txt
bin_fixedrec-1.0.1.dist-info/top_level.txt
bin_fixedrec-1.0.1.dist-info/RECORD
