Metadata-Version: 2.4
Name: bin-fixedrec
Version: 1.0.1
Summary: 固定長バイナリレコードをフィールドごとに分割して区切りテキスト形式で出力するツール。フィールドのバイト列はそのまま保持します。
Author: tsuutar
License: MIT
Project-URL: Homepage, https://github.com/tsuutar/fixedrec
Keywords: fixed-length,binary,record,parser,cli
Classifier: Programming Language :: Python :: 3
Classifier: Programming Language :: Python :: 3.10
Classifier: Programming Language :: Python :: 3.11
Classifier: Programming Language :: Python :: 3.12
Classifier: License :: OSI Approved :: MIT License
Classifier: Operating System :: OS Independent
Requires-Python: >=3.10
License-File: LICENSE
Provides-Extra: dev
Requires-Dist: pytest>=7.0; extra == "dev"
Requires-Dist: pytest-cov>=4.0; extra == "dev"
Dynamic: license-file
